htcondor_queue_poller.py
htcondor_queue_poller-0.1.1.dist-info/LICENSE
htcondor_queue_poller-0.1.1.dist-info/METADATA
htcondor_queue_poller-0.1.1.dist-info/WHEEL
htcondor_queue_poller-0.1.1.dist-info/entry_points.txt
htcondor_queue_poller-0.1.1.dist-info/RECORD
